mediaref/__init__.py
mediaref/_features.py
mediaref/_internal.py
mediaref/_typing.py
mediaref/_version.py
mediaref/batch.py
mediaref/core.py
mediaref/data_uri.py
mediaref/py.typed
mediaref/resource_cache.py
mediaref/cached_av/__init__.py
mediaref/cached_av/container_mixin.py
mediaref/cached_av/input_container_mixin.py
mediaref/video_decoder/__init__.py
mediaref/video_decoder/base.py
mediaref/video_decoder/frame_batch.py
mediaref/video_decoder/pyav_decoder.py
mediaref/video_decoder/torchcodec_decoder.py
mediaref/video_decoder/types.py
mediaref-0.4.3.dist-info/METADATA
mediaref-0.4.3.dist-info/WHEEL
mediaref-0.4.3.dist-info/licenses/LICENSE
mediaref-0.4.3.dist-info/RECORD
