Metadata-Version: 2.4
Name: mediaref
Version: 0.4.3
Summary: Pydantic media reference for images and video frames with lazy loading and optimized batch decoding
Author-email: Suhwan Choi <milkclouds00@gmail.com>
License-File: LICENSE
Classifier: Development Status :: 4 - Beta
Classifier: Intended Audience :: Developers
Classifier: Intended Audience :: Science/Research
Classifier: License :: OSI Approved :: MIT License
Classifier: Operating System :: OS Independent
Classifier: Programming Language :: Python :: 3
Classifier: Programming Language :: Python :: 3.9
Classifier: Programming Language :: Python :: 3.10
Classifier: Programming Language :: Python :: 3.11
Classifier: Programming Language :: Python :: 3.12
Classifier: Programming Language :: Python :: 3.13
Classifier: Topic :: Multimedia :: Graphics
Classifier: Topic :: Multimedia :: Video
Classifier: Topic :: Scientific/Engineering
Classifier: Topic :: Software Development :: Libraries :: Python Modules
Classifier: Typing :: Typed
Requires-Python: >=3.9
Requires-Dist: loguru
Requires-Dist: numpy
Requires-Dist: opencv-python
Requires-Dist: pillow>=9.4.0
Requires-Dist: pydantic>=2.0
Requires-Dist: requests>=2.32.2
Provides-Extra: video
Requires-Dist: av>=15.0; extra == 'video'
